vrtneopixel/__init__.py
vrtneopixel/vrtneopixel.py
vrtneopixel-1.1.3.dist-info/DESCRIPTION.rst
vrtneopixel-1.1.3.dist-info/METADATA
vrtneopixel-1.1.3.dist-info/RECORD
vrtneopixel-1.1.3.dist-info/WHEEL
vrtneopixel-1.1.3.dist-info/metadata.json
vrtneopixel-1.1.3.dist-info/top_level.txt
