Metadata-Version: 2.0
Name: vrtneopixel
Version: 1.1.3
Summary: A WS2812 matrix emulator
Home-page: https://github.com/Hackable-Magazine/vrtneopixel
Author: Tristan Colombo
Author-email: tristan.colombo@gmail.com
License: GPLv3+
Keywords: emulator ws2812 neopixel rpi_ws281x RaspberryPi
Platform: UNKNOWN
Classifier: Development Status :: 5 - Production/Stable
Classifier: Intended Audience :: Developers
Classifier: Topic :: System :: Emulators
Classifier: License :: OSI Approved :: GNU General Public License v3 or later (GPLv3+)
Classifier: Programming Language :: Python :: 3
Requires-Dist: pygame
